cloudformation_dataclasses/__init__.py
cloudformation_dataclasses/__version__.py
cloudformation_dataclasses/py.typed
cloudformation_dataclasses/aws/__init__.py
cloudformation_dataclasses/aws/accessanalyzer.py
cloudformation_dataclasses/aws/acmpca.py
cloudformation_dataclasses/aws/aiops.py
cloudformation_dataclasses/aws/amazonmq.py
cloudformation_dataclasses/aws/amplify.py
cloudformation_dataclasses/aws/amplifyuibuilder.py
cloudformation_dataclasses/aws/apigateway.py
cloudformation_dataclasses/aws/apigatewayv2.py
cloudformation_dataclasses/aws/appconfig.py
cloudformation_dataclasses/aws/appflow.py
cloudformation_dataclasses/aws/appintegrations.py
cloudformation_dataclasses/aws/applicationautoscaling.py
cloudformation_dataclasses/aws/applicationinsights.py
cloudformation_dataclasses/aws/applicationsignals.py
cloudformation_dataclasses/aws/appmesh.py
cloudformation_dataclasses/aws/apprunner.py
cloudformation_dataclasses/aws/appstream.py
cloudformation_dataclasses/aws/appsync.py
cloudformation_dataclasses/aws/apptest.py
cloudformation_dataclasses/aws/aps.py
cloudformation_dataclasses/aws/arcregionswitch.py
cloudformation_dataclasses/aws/arczonalshift.py
cloudformation_dataclasses/aws/athena.py
cloudformation_dataclasses/aws/auditmanager.py
cloudformation_dataclasses/aws/autoscaling.py
cloudformation_dataclasses/aws/autoscalingplans.py
cloudformation_dataclasses/aws/b2bi.py
cloudformation_dataclasses/aws/backup.py
cloudformation_dataclasses/aws/backupgateway.py
cloudformation_dataclasses/aws/batch.py
cloudformation_dataclasses/aws/bcmdataexports.py
cloudformation_dataclasses/aws/bedrock.py
cloudformation_dataclasses/aws/bedrockagentcore.py
cloudformation_dataclasses/aws/billing.py
cloudformation_dataclasses/aws/billingconductor.py
cloudformation_dataclasses/aws/budgets.py
cloudformation_dataclasses/aws/cassandra.py
cloudformation_dataclasses/aws/ce.py
cloudformation_dataclasses/aws/certificatemanager.py
cloudformation_dataclasses/aws/chatbot.py
cloudformation_dataclasses-0.3.4.dist-info/METADATA
cloudformation_dataclasses-0.3.4.dist-info/WHEEL
cloudformation_dataclasses-0.3.4.dist-info/licenses/LICENSE
cloudformation_dataclasses-0.3.4.dist-info/RECORD
