Metadata-Version: 2.4
Name: cloudformation_dataclasses
Version: 0.3.4
Summary: Python dataclasses for AWS CloudFormation template synthesis
Project-URL: Homepage, https://github.com/lex00/cloudformation_dataclasses
Project-URL: Repository, https://github.com/lex00/cloudformation_dataclasses
Project-URL: Issues, https://github.com/lex00/cloudformation_dataclasses/issues
Author-email: lex00 <121451605+lex00@users.noreply.github.com>
License: MIT
License-File: LICENSE
Keywords: aws,cloudformation,dataclasses,iac,infrastructure
Classifier: Development Status :: 3 - Alpha
Classifier: Intended Audience :: Developers
Classifier: License :: OSI Approved :: MIT License
Classifier: Programming Language :: Python :: 3
Classifier: Programming Language :: Python :: 3.13
Classifier: Topic :: Software Development :: Libraries :: Python Modules
Classifier: Topic :: System :: Systems Administration
Requires-Python: >=3.13
Provides-Extra: dev
Requires-Dist: black>=23.12; extra == 'dev'
Requires-Dist: botocore>=1.35.0; extra == 'dev'
Requires-Dist: mypy>=1.8; extra == 'dev'
Requires-Dist: pytest-cov>=4.1; extra == 'dev'
Requires-Dist: pytest>=7.4; extra == 'dev'
Requires-Dist: requests>=2.31; extra == 'dev'
Requires-Dist: ruff>=0.1; extra == 'dev'
Provides-Extra: yaml
Requires-Dist: pyyaml>=6.0; extra == 'yaml'
